{"nodes": [{"id": "mainactivity", "label": "MainActivity", "file_type": "code", "source_file": "app/src/main/java/it/lcavagnari/pdm/dermcalc/MainActivity.kt", "source_location": "class MainActivity", "source_url": null, "captured_at": null, "author": null, "contributor": null}], "edges": [{"source": "mainactivity", "target": "onboardingmodel", "relation": "calls", "confidence": "EXTRACTED", "confidence_score": 1.0, "source_file": "app/src/main/java/it/lcavagnari/pdm/dermcalc/MainActivity.kt", "source_location": "ViewModelProvider(this)[OnboardingModel::class.java]", "weight": 1.0}, {"source": "mainactivity", "target": "toolsmodel", "relation": "calls", "confidence": "EXTRACTED", "confidence_score": 1.0, "source_file": "app/src/main/java/it/lcavagnari/pdm/dermcalc/MainActivity.kt", "source_location": "ViewModelProvider(this)[ToolsModel::class.java]", "weight": 1.0}, {"source": "mainactivity", "target": "quotemodel", "relation": "calls", "confidence": "EXTRACTED", "confidence_score": 1.0, "source_file": "app/src/main/java/it/lcavagnari/pdm/dermcalc/MainActivity.kt", "source_location": "ViewModelProvider(this)[QuoteModel::class.java]", "weight": 1.0}, {"source": "mainactivity", "target": "mainportraitactivity", "relation": "calls", "confidence": "EXTRACTED", "confidence_score": 1.0, "source_file": "app/src/main/java/it/lcavagnari/pdm/dermcalc/MainActivity.kt", "source_location": "MainPortraitActivity(...)", "weight": 1.0}, {"source": "mainactivity", "target": "mainlandscapeactivity", "relation": "calls", "confidence": "EXTRACTED", "confidence_score": 1.0, "source_file": "app/src/main/java/it/lcavagnari/pdm/dermcalc/MainActivity.kt", "source_location": "MainLandscapeActivity(onboardingModel)", "weight": 1.0}], "hyperedges": [{"id": "viewmodel_trinity", "label": "Three ViewModels wired in MainActivity", "nodes": ["mainactivity", "onboardingmodel", "toolsmodel", "quotemodel"], "relation": "participate_in", "confidence": "EXTRACTED", "confidence_score": 1.0, "source_file": "app/src/main/java/it/lcavagnari/pdm/dermcalc/MainActivity.kt"}]}