{"nodes": [{"id": "toolsmodel", "label": "ToolsModel", "file_type": "code", "source_file": "app/src/main/java/it/lcavagnari/pdm/dermcalc/models/ToolsModel.kt", "source_location": "class ToolsModel", "source_url": null, "captured_at": null, "author": null, "contributor": null}, {"id": "toolresult", "label": "ToolResult (sealed interface)", "file_type": "code", "source_file": "app/src/main/java/it/lcavagnari/pdm/dermcalc/models/ToolsModel.kt", "source_location": "sealed interface ToolResult", "source_url": null, "captured_at": null, "author": null, "contributor": null}, {"id": "pasiresult", "label": "PasiResult", "file_type": "code", "source_file": "app/src/main/java/it/lcavagnari/pdm/dermcalc/models/ToolsModel.kt", "source_location": "data class PasiResult", "source_url": null, "captured_at": null, "author": null, "contributor": null}, {"id": "easiresult", "label": "EasiResult", "file_type": "code", "source_file": "app/src/main/java/it/lcavagnari/pdm/dermcalc/models/ToolsModel.kt", "source_location": "data class EasiResult", "source_url": null, "captured_at": null, "author": null, "contributor": null}, {"id": "bmiresult", "label": "BmiResult", "file_type": "code", "source_file": "app/src/main/java/it/lcavagnari/pdm/dermcalc/models/ToolsModel.kt", "source_location": "data class BmiResult", "source_url": null, "captured_at": null, "author": null, "contributor": null}, {"id": "bsaresult", "label": "BsaResult", "file_type": "code", "source_file": "app/src/main/java/it/lcavagnari/pdm/dermcalc/models/ToolsModel.kt", "source_location": "data class BsaResult", "source_url": null, "captured_at": null, "author": null, "contributor": null}], "edges": [{"source": "pasiresult", "target": "toolresult", "relation": "implements", "confidence": "EXTRACTED", "confidence_score": 1.0, "source_file": "app/src/main/java/it/lcavagnari/pdm/dermcalc/models/ToolsModel.kt", "source_location": "data class PasiResult : ToolResult", "weight": 1.0}, {"source": "easiresult", "target": "toolresult", "relation": "implements", "confidence": "EXTRACTED", "confidence_score": 1.0, "source_file": "app/src/main/java/it/lcavagnari/pdm/dermcalc/models/ToolsModel.kt", "source_location": "data class EasiResult : ToolResult", "weight": 1.0}, {"source": "bmiresult", "target": "toolresult", "relation": "implements", "confidence": "EXTRACTED", "confidence_score": 1.0, "source_file": "app/src/main/java/it/lcavagnari/pdm/dermcalc/models/ToolsModel.kt", "source_location": "data class BmiResult : ToolResult", "weight": 1.0}, {"source": "bsaresult", "target": "toolresult", "relation": "implements", "confidence": "EXTRACTED", "confidence_score": 1.0, "source_file": "app/src/main/java/it/lcavagnari/pdm/dermcalc/models/ToolsModel.kt", "source_location": "data class BsaResult : ToolResult", "weight": 1.0}, {"source": "toolsmodel", "target": "toolresult", "relation": "shares_data_with", "confidence": "EXTRACTED", "confidence_score": 1.0, "source_file": "app/src/main/java/it/lcavagnari/pdm/dermcalc/models/ToolsModel.kt", "source_location": "MutableStateFlow<List<ToolResult>>", "weight": 1.0}], "hyperedges": [{"id": "toolresult_subtypes", "label": "ToolResult sealed interface with four clinical subtypes", "nodes": ["toolresult", "pasiresult", "easiresult", "bmiresult", "bsaresult"], "relation": "implement", "confidence": "EXTRACTED", "confidence_score": 1.0, "source_file": "app/src/main/java/it/lcavagnari/pdm/dermcalc/models/ToolsModel.kt"}]}