{"nodes": [{"id": "readme_dermcalc", "label": "DermCalc README", "file_type": "document", "source_file": "README.md", "source_location": null, "source_url": null, "captured_at": null, "author": null, "contributor": null}, {"id": "readme_feature_bmi", "label": "BMI Calculator Feature", "file_type": "rationale", "source_file": "README.md", "source_location": "line 7", "source_url": null, "captured_at": null, "author": null, "contributor": null}, {"id": "readme_feature_bsa", "label": "BSA Calculator Feature", "file_type": "rationale", "source_file": "README.md", "source_location": "line 8", "source_url": null, "captured_at": null, "author": null, "contributor": null}, {"id": "readme_feature_pasi", "label": "PASI Calculator Feature", "file_type": "rationale", "source_file": "README.md", "source_location": "line 9", "source_url": null, "captured_at": null, "author": null, "contributor": null}, {"id": "readme_feature_easi", "label": "EASI Calculator Feature", "file_type": "rationale", "source_file": "README.md", "source_location": "line 10", "source_url": null, "captured_at": null, "author": null, "contributor": null}, {"id": "readme_feature_history", "label": "History Feature", "file_type": "rationale", "source_file": "README.md", "source_location": "line 11", "source_url": null, "captured_at": null, "author": null, "contributor": null}, {"id": "readme_theme_undertale", "label": "Undertale-Inspired Material3 Theme", "file_type": "rationale", "source_file": "README.md", "source_location": "line 24", "source_url": null, "captured_at": null, "author": null, "contributor": null}, {"id": "readme_severity_color_mapping", "label": "Severity Color Mapping (Mild/Moderate/Severe)", "file_type": "rationale", "source_file": "README.md", "source_location": "line 32", "source_url": null, "captured_at": null, "author": null, "contributor": null}, {"id": "readme_dark_mode", "label": "Dark/Light Mode Support", "file_type": "rationale", "source_file": "README.md", "source_location": "line 38", "source_url": null, "captured_at": null, "author": null, "contributor": null}, {"id": "readme_release_pipeline", "label": "GitHub Actions Release Pipeline", "file_type": "rationale", "source_file": "README.md", "source_location": "line 64", "source_url": null, "captured_at": null, "author": null, "contributor": null}, {"id": "readme_signing_secrets", "label": "Android Signing Secrets (GitHub Actions)", "file_type": "rationale", "source_file": "README.md", "source_location": "line 71", "source_url": null, "captured_at": null, "author": null, "contributor": null}], "edges": [{"source": "readme_dermcalc", "target": "readme_feature_bmi", "relation": "references", "confidence": "EXTRACTED", "confidence_score": 1.0, "source_file": "README.md", "source_location": "line 7", "weight": 1.0}, {"source": "readme_dermcalc", "target": "readme_feature_bsa", "relation": "references", "confidence": "EXTRACTED", "confidence_score": 1.0, "source_file": "README.md", "source_location": "line 8", "weight": 1.0}, {"source": "readme_dermcalc", "target": "readme_feature_pasi", "relation": "references", "confidence": "EXTRACTED", "confidence_score": 1.0, "source_file": "README.md", "source_location": "line 9", "weight": 1.0}, {"source": "readme_dermcalc", "target": "readme_feature_easi", "relation": "references", "confidence": "EXTRACTED", "confidence_score": 1.0, "source_file": "README.md", "source_location": "line 10", "weight": 1.0}, {"source": "readme_dermcalc", "target": "readme_feature_history", "relation": "references", "confidence": "EXTRACTED", "confidence_score": 1.0, "source_file": "README.md", "source_location": "line 11", "weight": 1.0}, {"source": "readme_dermcalc", "target": "readme_theme_undertale", "relation": "references", "confidence": "EXTRACTED", "confidence_score": 1.0, "source_file": "README.md", "source_location": "line 24", "weight": 1.0}, {"source": "readme_theme_undertale", "target": "readme_severity_color_mapping", "relation": "conceptually_related_to", "confidence": "EXTRACTED", "confidence_score": 1.0, "source_file": "README.md", "source_location": "line 32", "weight": 1.0}, {"source": "readme_theme_undertale", "target": "readme_dark_mode", "relation": "conceptually_related_to", "confidence": "EXTRACTED", "confidence_score": 1.0, "source_file": "README.md", "source_location": "line 38", "weight": 1.0}, {"source": "readme_dermcalc", "target": "readme_release_pipeline", "relation": "references", "confidence": "EXTRACTED", "confidence_score": 1.0, "source_file": "README.md", "source_location": "line 64", "weight": 1.0}, {"source": "readme_release_pipeline", "target": "wf_release_pipeline", "relation": "references", "confidence": "EXTRACTED", "confidence_score": 1.0, "source_file": "README.md", "source_location": "line 64", "weight": 1.0}, {"source": "readme_release_pipeline", "target": "readme_signing_secrets", "relation": "references", "confidence": "EXTRACTED", "confidence_score": 1.0, "source_file": "README.md", "source_location": "line 71", "weight": 1.0}, {"source": "readme_signing_secrets", "target": "wf_secret_keystore_b64", "relation": "conceptually_related_to", "confidence": "INFERRED", "confidence_score": 0.95, "source_file": "README.md", "source_location": "line 73", "weight": 0.95}, {"source": "readme_signing_secrets", "target": "wf_secret_nvd_api_key", "relation": "conceptually_related_to", "confidence": "INFERRED", "confidence_score": 0.95, "source_file": "README.md", "source_location": "line 79", "weight": 0.95}, {"source": "readme_feature_pasi", "target": "readme_severity_color_mapping", "relation": "conceptually_related_to", "confidence": "INFERRED", "confidence_score": 0.85, "source_file": "README.md", "source_location": "line 9", "weight": 0.85}, {"source": "readme_feature_easi", "target": "readme_severity_color_mapping", "relation": "conceptually_related_to", "confidence": "INFERRED", "confidence_score": 0.85, "source_file": "README.md", "source_location": "line 10", "weight": 0.85}], "hyperedges": []}