{"nodes": [{"id": "wf_release_pipeline", "label": "Android Release Pipeline Workflow", "file_type": "code", "source_file": ".github/workflows/android-release-pipeline.yml", "source_location": null, "source_url": null, "captured_at": null, "author": null, "contributor": null}, {"id": "wf_change_detection", "label": "Source Change Detection Job", "file_type": "rationale", "source_file": ".github/workflows/android-release-pipeline.yml", "source_location": "line 21", "source_url": null, "captured_at": null, "author": null, "contributor": null}, {"id": "wf_cron_schedule", "label": "Daily Cron Schedule (0 0 * * *)", "file_type": "rationale", "source_file": ".github/workflows/android-release-pipeline.yml", "source_location": "line 6", "source_url": null, "captured_at": null, "author": null, "contributor": null}], "edges": [{"source": "wf_release_pipeline", "target": "wf_unit_tests", "relation": "calls", "confidence": "EXTRACTED", "confidence_score": 1.0, "source_file": ".github/workflows/android-release-pipeline.yml", "source_location": "line 84", "weight": 1.0}, {"source": "wf_release_pipeline", "target": "wf_lint", "relation": "calls", "confidence": "EXTRACTED", "confidence_score": 1.0, "source_file": ".github/workflows/android-release-pipeline.yml", "source_location": "line 90", "weight": 1.0}, {"source": "wf_release_pipeline", "target": "wf_security_review", "relation": "calls", "confidence": "EXTRACTED", "confidence_score": 1.0, "source_file": ".github/workflows/android-release-pipeline.yml", "source_location": "line 96", "weight": 1.0}, {"source": "wf_release_pipeline", "target": "wf_signed_release", "relation": "calls", "confidence": "EXTRACTED", "confidence_score": 1.0, "source_file": ".github/workflows/android-release-pipeline.yml", "source_location": "line 104", "weight": 1.0}, {"source": "wf_release_pipeline", "target": "wf_change_detection", "relation": "references", "confidence": "EXTRACTED", "confidence_score": 1.0, "source_file": ".github/workflows/android-release-pipeline.yml", "source_location": "line 21", "weight": 1.0}, {"source": "wf_release_pipeline", "target": "wf_cron_schedule", "relation": "references", "confidence": "EXTRACTED", "confidence_score": 1.0, "source_file": ".github/workflows/android-release-pipeline.yml", "source_location": "line 6", "weight": 1.0}, {"source": "wf_release_pipeline", "target": "wf_change_detection", "relation": "calls", "confidence": "EXTRACTED", "confidence_score": 1.0, "source_file": ".github/workflows/android-release-pipeline.yml", "source_location": "line 53", "weight": 1.0}], "hyperedges": [{"id": "release_pipeline_gating", "label": "Release Pipeline Quality Gate (unit-tests + lint + security \u2192 signed-release)", "nodes": ["wf_unit_tests", "wf_lint", "wf_security_review", "wf_signed_release"], "relation": "participate_in", "confidence": "EXTRACTED", "confidence_score": 1.0, "source_file": ".github/workflows/android-release-pipeline.yml"}]}